<?xml version="1.0" encoding="utf-8"?>
<hibernate-mapping xmlns="urn:nhibernate-mapping-2.2" assembly="AdminApp" namespace="AdminApp.Dominio">
	
	<class name="ProduktuHistorikoa, AdminApp" table="produktuhistorikoa">

		<id name="Id" column="id" type="int">
			<generator class="identity"/>
		</id>

		<property name="ProduktuaId" column="produktua_id" type="int"/>

		<property name="ErabiltzaileaId" column="erabiltzailea_id" type="int" />

		<property name="Data" column="data" type="datetime" />

		<property name="Ekintza" column="ekintza" type="string"/>

		<property name="Galera" column="galera" type="int"/>
	</class>
</hibernate-mapping>
